anfis/__init__.py
anfis/anfis.py
anfis/tests.py
anfis/trainingSet.txt
anfis/membership/__init__.py
anfis/membership/membershipfunction.py
anfis/membership/mfDerivs.py
anfis-0.3.1.dist-info/METADATA
anfis-0.3.1.dist-info/RECORD
anfis-0.3.1.dist-info/WHEEL
anfis-0.3.1.dist-info/top_level.txt
